MANIFEST.in
NEWS.txt
README.rst
setup.py
src/pywhmcs/__init__.py
src/pywhmcs/whmcs.py
src/pywhmcs.egg-info/PKG-INFO
src/pywhmcs.egg-info/SOURCES.txt
src/pywhmcs.egg-info/dependency_links.txt
src/pywhmcs.egg-info/entry_points.txt
src/pywhmcs.egg-info/not-zip-safe
src/pywhmcs.egg-info/requires.txt
src/pywhmcs.egg-info/top_level.txt