Metadata-Version: 1.1
Name: pywhmcs
Version: 0.0.2
Summary: WHMCS Client Library
Home-page: https://github.com/zekzekus/pywhmcs
Author: Zekeriya Koc
Author-email: zekzekus@gmail.com
License: Gnu General Public License v3
Keywords: whmcs library http api
Platform: UNKNOWN
Classifier: Development Status :: 1 - Planning
Classifier: Development Status :: 2 - Pre-Alpha
Classifier: Environment :: Console
Classifier: Intended Audience :: Developers
Classifier: Intended Audience :: System Administrators
Classifier: License :: OSI Approved :: GNU General Public License v3 (GPLv3)
Classifier: Natural Language :: English
Classifier: Natural Language :: Turkish
Classifier: Operating System :: Microsoft :: Windows
Classifier: Operating System :: POSIX :: Linux
Classifier: Programming Language :: Python :: 2.7
Classifier: Topic :: Internet :: WWW/HTTP
